transport_analysis/__init__.py
transport_analysis/_version.py
transport_analysis/due.py
transport_analysis/velocityautocorr.py
transport_analysis/viscosity.py
transport_analysis/data/README.md
transport_analysis/data/__init__.py
transport_analysis/data/files.py
transport_analysis/data/mda.txt
transport_analysis/data/ethylene_carbonate/.trajectory.trr_offsets.lock
transport_analysis/data/ethylene_carbonate/.trajectory.trr_offsets.npz
transport_analysis/data/ethylene_carbonate/topology.pdb
transport_analysis/data/ethylene_carbonate/trajectory.trr
transport_analysis/tests/__init__.py
transport_analysis/tests/conftest.py
transport_analysis/tests/test_transport_analysis.py
transport_analysis/tests/test_velocityautocorr.py
transport_analysis/tests/test_viscosity.py
transport_analysis/tests/utils.py
transport_analysis-0.1.2.dist-info/AUTHORS.md
transport_analysis-0.1.2.dist-info/LICENSE
transport_analysis-0.1.2.dist-info/METADATA
transport_analysis-0.1.2.dist-info/WHEEL
transport_analysis-0.1.2.dist-info/top_level.txt
transport_analysis-0.1.2.dist-info/RECORD
