Metadata-Version: 2.1
Name: transport_analysis
Version: 0.1.2
Summary: A Python package to compute and analyze transport properties.
Author: Xu Hong Chen
Author-email: Xu Hong Chen <xhgchen@gmail.com>
Maintainer-email: Xu Hong Chen <xhgchen@gmail.com>
License: GNU GENERAL PUBLIC LICENSE
Keywords: molecular simulations
Requires-Python: >=3.10
License-File: LICENSE
License-File: AUTHORS.md
Requires-Dist: MDAnalysis>=2.1.0
Requires-Dist: tidynamics>=1.0.0
Provides-Extra: doc
Requires-Dist: sphinx; extra == "doc"
Requires-Dist: sphinx-rtd-theme; extra == "doc"
Provides-Extra: test
Requires-Dist: pytest>=6.0; extra == "test"
Requires-Dist: pytest-xdist>=2.5; extra == "test"
Requires-Dist: pytest-cov>=3.0; extra == "test"
Requires-Dist: MDAnalysisTests>=2.0.0; extra == "test"
